SeeMee/__init__.py
SeeMee/__main__.py
SeeMee/arguments.py
SeeMee/base.pyd
SeeMee/info.py
SeeMee-0.5.2.dist-info/LICENSE
SeeMee-0.5.2.dist-info/METADATA
SeeMee-0.5.2.dist-info/WHEEL
SeeMee-0.5.2.dist-info/entry_points.txt
SeeMee-0.5.2.dist-info/top_level.txt
SeeMee-0.5.2.dist-info/RECORD
