Metadata-Version: 2.1
Name: SeeMee
Version: 0.5.2
Summary: Application which detects which camera you're looking at
Home-page: https://github.com/gaming32/SeeMee
Author: Gaming32
Author-email: gaming32i64@gmail.com
License: License :: OSI Approved :: MIT License
Platform: UNKNOWN
Requires-Python: >=2.7, !=3.0.*, !=3.1.*, !=3.2.*, !=3.3.*
Requires-Dist: tensorflow
Requires-Dist: pygame
Requires-Dist: VideoCapture ; platform_system == "Windows"
